pysendpulse/__init__.py
pysendpulse/pysendpulse.py
pysendpulse-0.1.7.dist-info/LICENSE.md
pysendpulse-0.1.7.dist-info/METADATA
pysendpulse-0.1.7.dist-info/WHEEL
pysendpulse-0.1.7.dist-info/top_level.txt
pysendpulse-0.1.7.dist-info/RECORD
