Metadata-Version: 2.1
Name: pysendpulse
Version: 0.1.7
Summary: A simple SendPulse REST client library and example for Python
Home-page: https://github.com/sendpulse/sendpulse-rest-api-python
Author: Maksym Ustymenko
Author-email: tech@sendpulse.com
License-File: LICENSE.md
Requires-Dist: python3-memcached
Requires-Dist: requests
Requires-Dist: deprecated
